Metadata-Version: 1.1
Name: vpscrape
Version: 0.0.1
Summary: Web scraping based on selenium. supported for several website to do instantly webscraping with less code
Home-page: UNKNOWN
Author: Vinson Phoan
Author-email: contact@vinsonphoan.com
License: MIT
Keywords: scrape,web scraping,news scraper,scraper
Platform: UNKNOWN
Classifier: Development Status :: 5 - Production/Stable
Classifier: Intended Audience :: Education
Classifier: Operating System :: Microsoft :: Windows :: Windows 10
Classifier: License :: OSI Approved :: MIT License
Classifier: Programming Language :: Python :: 3
